geronimo/__init__.py
geronimo/analyzers/__init__.py
geronimo/analyzers/base.py
geronimo/analyzers/deterministic.py
geronimo/analyzers/sdk_wrapper.py
geronimo/artifacts/__init__.py
geronimo/artifacts/mlflow_backend.py
geronimo/artifacts/protocol.py
geronimo/artifacts/store.py
geronimo/batch/__init__.py
geronimo/batch/pipeline.py
geronimo/batch/schedule.py
geronimo/cli/__init__.py
geronimo/cli/import_cmd.py
geronimo/cli/keys_cmd.py
geronimo/cli/main.py
geronimo/config/__init__.py
geronimo/config/loader.py
geronimo/config/schema.py
geronimo/data/__init__.py
geronimo/data/connection.py
geronimo/data/query.py
geronimo/data/source.py
geronimo/deploy/__init__.py
geronimo/deploy/config.py
geronimo/deploy/protocol.py
geronimo/deploy/targets.py
geronimo/deploy/providers/__init__.py
geronimo/deploy/providers/aws.py
geronimo/deploy/providers/azure.py
geronimo/deploy/providers/gcp.py
geronimo/features/__init__.py
geronimo/features/base.py
geronimo/features/feature.py
geronimo/generators/__init__.py
geronimo/generators/base.py
geronimo/generators/docker.py
geronimo/generators/metaflow.py
geronimo/generators/pipeline.py
geronimo/generators/project.py
geronimo/generators/terraform.py
geronimo/mcp/__init__.py
geronimo/mcp/server.py
geronimo/mcp/tools.py
geronimo/models/__init__.py
geronimo/models/base.py
geronimo/models/params.py
geronimo/monitoring/api.py
geronimo/monitoring/drift_models.py
geronimo/monitoring/snapshot.py
geronimo/pipelines/__init__.py
geronimo/scanners/__init__.py
geronimo/scanners/project.py
geronimo/serving/__init__.py
geronimo/serving/endpoint.py
geronimo/serving/auth/__init__.py
geronimo/serving/auth/config.py
geronimo/serving/auth/keys.py
geronimo/serving/auth/middleware.py
geronimo/templates/.gitkeep
geronimo/templates/agent/server.py
geronimo/templates/monitoring/__init__.py
geronimo/templates/monitoring/alerts.py
geronimo/templates/monitoring/drift.py
geronimo/templates/monitoring/metrics.py
geronimo/templates/monitoring/middleware.py
geronimo-0.3.0.dist-info/METADATA
geronimo-0.3.0.dist-info/WHEEL
geronimo-0.3.0.dist-info/entry_points.txt
geronimo-0.3.0.dist-info/licenses/LICENSE
geronimo-0.3.0.dist-info/RECORD
