Metadata-Version: 2.4
Name: geronimo
Version: 0.3.0
Summary: ML deployment framework - from local development to production with one command
Project-URL: Homepage, https://geronimo.dev
Project-URL: Documentation, https://geronimo.dev/docs
Project-URL: Repository, https://github.com/geronimo-deploy-cloud/geronimo
Project-URL: Changelog, https://github.com/geronimo-deploy-cloud/geronimo/releases
Author-email: Chris Sweet <chris.sweet0320@gmail.com>
License: Apache-2.0
License-File: LICENSE
Keywords: ai-agents,deployment,machine-learning,mcp,mlops,model-serving
Classifier: Development Status :: 3 - Alpha
Classifier: Intended Audience :: Developers
Classifier: License :: OSI Approved :: Apache Software License
Classifier: Programming Language :: Python :: 3
Classifier: Programming Language :: Python :: 3.11
Classifier: Programming Language :: Python :: 3.12
Classifier: Topic :: Scientific/Engineering :: Artificial Intelligence
Classifier: Topic :: Software Development :: Libraries :: Python Modules
Requires-Python: >=3.11
Requires-Dist: jinja2>=3.1.6
Requires-Dist: pandas>=2.0.0
Requires-Dist: pydantic>=2.12.5
Requires-Dist: pyyaml>=6.0.3
Requires-Dist: rich>=14.2.0
Requires-Dist: typer>=0.21.1
Provides-Extra: all
Requires-Dist: mlflow>=2.10.0; extra == 'all'
Requires-Dist: psycopg2-binary>=2.9.0; extra == 'all'
Requires-Dist: pulumi-aws>=6.0.0; extra == 'all'
Requires-Dist: pulumi-azure-native>=2.0.0; extra == 'all'
Requires-Dist: pulumi-gcp>=7.0.0; extra == 'all'
Requires-Dist: pulumi>=3.0.0; extra == 'all'
Requires-Dist: pyodbc>=5.0.0; extra == 'all'
Requires-Dist: snowflake-connector-python>=3.0.0; extra == 'all'
Provides-Extra: cloud
Requires-Dist: httpx>=0.25.0; extra == 'cloud'
Provides-Extra: databases
Requires-Dist: psycopg2-binary>=2.9.0; extra == 'databases'
Requires-Dist: pyodbc>=5.0.0; extra == 'databases'
Requires-Dist: snowflake-connector-python>=3.0.0; extra == 'databases'
Provides-Extra: mlflow
Requires-Dist: mlflow>=2.10.0; extra == 'mlflow'
Provides-Extra: pulumi
Requires-Dist: pulumi-aws>=6.0.0; extra == 'pulumi'
Requires-Dist: pulumi-azure-native>=2.0.0; extra == 'pulumi'
Requires-Dist: pulumi-gcp>=7.0.0; extra == 'pulumi'
Requires-Dist: pulumi>=3.0.0; extra == 'pulumi'
